symclatron/__init__.py
symclatron/__main__.py
symclatron/symclatron.py
symclatron-0.9.3.dist-info/entry_points.txt
symclatron-0.9.3.dist-info/licenses/LICENSE
symclatron-0.9.3.dist-info/WHEEL
symclatron-0.9.3.dist-info/METADATA
symclatron-0.9.3.dist-info/RECORD
