Metadata-Version: 2.4
Name: symclatron
Version: 0.9.3
Summary: symclatron: symbiont classifier
Keywords: bioinformatics,machine-learning,symbiosis,microbiology,classification,genomics
Author-email: "Juan C. Villada" <jvillada@lbl.gov>
Requires-Python: >=3.12
Classifier: Intended Audience :: Science/Research
Classifier: Topic :: Scientific/Engineering :: Bio-Informatics
Classifier: Programming Language :: Python :: 3.12
Classifier: Operating System :: POSIX :: Linux
License-File: LICENSE
Requires-Dist: typer>=0.12.3
Requires-Dist: pandas>=2.2.2
Requires-Dist: numpy>=1.26.4
Requires-Dist: xgboost>=2.1.1
Requires-Dist: shap>=0.45.1
Requires-Dist: scikit-learn>=1.5.1
Requires-Dist: tensorflow-cpu>=2.18.0
Requires-Dist: joblib>=1.4.2
Requires-Dist: pyhmmer>=0.11.1
Requires-Dist: pyrodigal>=3.6.0
Requires-Dist: psutil>=5.9.0
Project-URL: Bug Tracker, https://github.com/NeLLi-team/symclatron/issues
Project-URL: Documentation, https://github.com/NeLLi-team/symclatron#readme
Project-URL: Homepage, https://github.com/NeLLi-team/symclatron
Project-URL: Repository, https://github.com/NeLLi-team/symclatron
